zsimparse/__init__.py
zsimparse/base_data_dict.py
zsimparse/basic.py
zsimparse/cache.py
zsimparse/cache_stat.py
zsimparse/config.py
zsimparse/h5stat.py
zsimparse/util.py
zsimparse/tests/__init__.py
zsimparse/tests/test_basic.py
zsimparse/tests/test_cache.py
zsimparse/tests/test_util.py
zsimparse/tests/simdir/heartbeat
zsimparse/tests/simdir/out.cfg
zsimparse/tests/simdir/zsim-cmp.h5
zsimparse/tests/simdir/zsim-ev.h5
zsimparse/tests/simdir/zsim.h5
zsimparse/tests/simdir/zsim.out
zsimparse-0.2.0.dist-info/DESCRIPTION.rst
zsimparse-0.2.0.dist-info/METADATA
zsimparse-0.2.0.dist-info/RECORD
zsimparse-0.2.0.dist-info/WHEEL
zsimparse-0.2.0.dist-info/metadata.json
zsimparse-0.2.0.dist-info/top_level.txt
