Metadata-Version: 2.0
Name: zsimparse
Version: 0.2.0
Summary: Python utilities to parse zsim simulation results
Home-page: https://github.com/gaomy3832/zsimparse
Author: Mingyu Gao
Author-email: gaomy@tsinghua.edu.cn
License: BSD 3-clause
Keywords: zsim parse libconfig hdf5
Platform: UNKNOWN
Classifier: Development Status :: 3 - Alpha
Classifier: Intended Audience :: Developers
Classifier: Intended Audience :: Science/Research
Classifier: License :: OSI Approved :: BSD License
Classifier: Programming Language :: Python :: 3.5
Classifier: Programming Language :: Python :: 3.6
Classifier: Programming Language :: Python :: 3.7
Classifier: Topic :: System :: Hardware
Classifier: Topic :: Utilities
Requires-Dist: coverage (>=5)
Requires-Dist: h5py (>=2.10.0)
Requires-Dist: libconf (>=2.0.0)
Requires-Dist: numpy (>=1.7)
Requires-Dist: pytest (>=3)
Requires-Dist: pytest-cov (>=2)
Requires-Dist: pytest-xdist (>=2)
